MANIFEST.in
README.txt
pdf.c
pyproject.toml
readpdfutils.c
setup.py
utils.c
wrapper.h
include/fpdf_annot.h
include/fpdf_attachment.h
include/fpdf_catalog.h
include/fpdf_dataavail.h
include/fpdf_doc.h
include/fpdf_edit.h
include/fpdf_ext.h
include/fpdf_flatten.h
include/fpdf_formfill.h
include/fpdf_fwlevent.h
include/fpdf_javascript.h
include/fpdf_ppo.h
include/fpdf_progressive.h
include/fpdf_save.h
include/fpdf_searchex.h
include/fpdf_signature.h
include/fpdf_structtree.h
include/fpdf_sysfontinfo.h
include/fpdf_text.h
include/fpdf_thumbnail.h
include/fpdf_transformpage.h
include/fpdfview.h
include/cpp/fpdf_deleters.h
include/cpp/fpdf_scopers.h
lib/libpdfium.so
lib/mac-arm64/.DS_Store
lib/mac-arm64/libpdfium.dylib
lib/macosx-11.0-arm64/libpdfium.dylib
readpdfutils.egg-info/PKG-INFO
readpdfutils.egg-info/SOURCES.txt
readpdfutils.egg-info/dependency_links.txt
readpdfutils.egg-info/requires.txt
readpdfutils.egg-info/top_level.txt