Metadata-Version: 2.2
Name: readpdfutils
Version: 1.0.4
Requires-Dist: numpy>=1.2.2
